[
  {
    "name": "empty",
    "x": -3901.5,
    "y": 1100.0017,
    "z": -3899.9983,
    "pitch": 0,
    "yaw": 0,
    "roll": 0
  },
  {
    "name": "rd_island1",
    "x": -3900.063,
    "y": 1099.9987,
    "z": -3898.5012,
    "pitch": 0,
    "yaw": 0,
    "roll": 0
  },
  {
    "name": "rd_r1",
    "x": -3899.9136,
    "y": 1113.5745,
    "z": -3897.7422,
    "pitch": 0,
    "yaw": 0,
    "roll": 0
  },
  {
    "name": "rd_sta1",
    "x": -3885.6343,
    "y": 1079.3196,
    "z": -3906.482,
    "pitch": 0,
    "yaw": 0,
    "roll": 0
  },
  {
    "name": "rd_vil1",
    "x": -3880.2468,
    "y": 1078.8721,
    "z": -3893.067,
    "pitch": -6.2845483,
    "yaw": 0.033061653,
    "roll": -6.2845483
  },
  {
    "name": "edoor",
    "x": -3883.821,
    "y": 1074.4639,
    "z": -3899.467,
    "pitch": -6.283613,
    "yaw": 0.03333375,
    "roll": -6.283613
  },
  {
    "name": "char19",
    "x": -3902.834,
    "y": 1113.5352,
    "z": -3898.8381,
    "pitch": -6.283295,
    "yaw": -1.4136317,
    "roll": -6.283295
  },
  {
    "name": "edoor",
    "x": -3903.6348,
    "y": 1112.473,
    "z": -3898.8672,
    "pitch": -6.2833066,
    "yaw": -4.6873317,
    "roll": -6.2833066
  },
  {
    "name": "char19",
    "x": -3883.834,
    "y": 1075.9979,
    "z": -3900.8474,
    "pitch": -6.283548,
    "yaw": -3.1361127,
    "roll": -6.283548
  },
  {
    "name": "tree11",
    "x": -3904.2827,
    "y": 1076.3529,
    "z": -3888.1335,
    "pitch": -6.28319,
    "yaw": -1.4662949E-06,
    "roll": -6.28319
  },
  {
    "name": "tree13",
    "x": -3895.597,
    "y": 1076.232,
    "z": -3854.6929,
    "pitch": 0,
    "yaw": 0,
    "roll": 0
  },
  {
    "name": "ct_chest2",
    "x": -3898.1392,
    "y": 1113.5522,
    "z": -3899.4968,
    "pitch": -6.28375,
    "yaw": -3.1177154,
    "roll": -6.28375
  },
  {
    "name": "empty",
    "x": -3896.917,
    "y": 1111.2717,
    "z": -3894.584,
    "pitch": 0,
    "yaw": 0,
    "roll": 0
  },
  {
    "name": "empty",
    "x": -3896.917,
    "y": 1111.2717,
    "z": -3894.584,
    "pitch": 0,
    "yaw": 0,
    "roll": 0
  },
  {
    "name": "empty",
    "x": -3903.3228,
    "y": 1111.2717,
    "z": -3895.3901,
    "pitch": 0,
    "yaw": 0,
    "roll": 0
  },
  {
    "name": "empty",
    "x": -3897.608,
    "y": 1112.4929,
    "z": -3896.5776,
    "pitch": 8.426294E-34,
    "yaw": 4.6653503E-38,
    "roll": 0
  },
  {
    "name": "tree13",
    "x": -3880.0457,
    "y": 1076.232,
    "z": -3855.8372,
    "pitch": 0,
    "yaw": 0,
    "roll": 0
  },
  {
    "name": "tree13",
    "x": -3874.29,
    "y": 1076.232,
    "z": -3859.0996,
    "pitch": 0,
    "yaw": 0,
    "roll": 0
  },
  {
    "name": "tree12",
    "x": -3869.6685,
    "y": 1076.9043,
    "z": -3880.002,
    "pitch": -6.283226,
    "yaw": -0.25683478,
    "roll": -6.283226
  },
  {
    "name": "tree12",
    "x": -3859.16,
    "y": 1076.9043,
    "z": -3883.2317,
    "pitch": -6.2832184,
    "yaw": -1.2761245,
    "roll": -6.2832184
  },
  {
    "name": "tree12",
    "x": -3863.2751,
    "y": 1076.9043,
    "z": -3896.9714,
    "pitch": -6.2832284,
    "yaw": -1.7448554,
    "roll": -6.2832284
  },
  {
    "name": "tree12",
    "x": -3861.782,
    "y": 1076.9043,
    "z": -3870.3713,
    "pitch": -6.283221,
    "yaw": -2.7269518,
    "roll": -6.283221
  },
  {
    "name": "tree12",
    "x": -3873.2026,
    "y": 1076.9043,
    "z": -3869.3052,
    "pitch": 0,
    "yaw": -2.7269518,
    "roll": 0
  },
  {
    "name": "portal1",
    "x": -3904.6804,
    "y": 1078.9182,
    "z": -3939.2048,
    "pitch": -6.2834935,
    "yaw": -0.889186,
    "roll": -6.2834935
  },
  {
    "name": "char19",
    "x": -3905.431,
    "y": 1078.8582,
    "z": -3935.5242,
    "pitch": -6.283324,
    "yaw": 0.36079365,
    "roll": -6.283324
  },
  {
    "name": "tree12",
    "x": -3877.2935,
    "y": 1076.9043,
    "z": -3858.2043,
    "pitch": 0,
    "yaw": -3.0654843,
    "roll": 0
  },
  {
    "name": "tree12",
    "x": -3892.6128,
    "y": 1076.9043,
    "z": -3853.5435,
    "pitch": -6.2832146,
    "yaw": -3.6458187,
    "roll": -6.2832146
  },
  {
    "name": "tree12",
    "x": -3908.7007,
    "y": 1076.9043,
    "z": -3857.4717,
    "pitch": 0,
    "yaw": -3.6458187,
    "roll": 0
  },
  {
    "name": "tree11",
    "x": -3870.964,
    "y": 1076.5079,
    "z": -3887.2666,
    "pitch": 0,
    "yaw": 0,
    "roll": 0
  },
  {
    "name": "tree11",
    "x": -3865.583,
    "y": 1076.5079,
    "z": -3891.179,
    "pitch": -6.2832203,
    "yaw": -0.6138115,
    "roll": -6.2832203
  },
  {
    "name": "tree11",
    "x": -3856.8638,
    "y": 1076.5079,
    "z": -3891.7786,
    "pitch": 0,
    "yaw": -0.6138115,
    "roll": 0
  },
  {
    "name": "tree11",
    "x": -3862.6404,
    "y": 1076.5079,
    "z": -3877.1797,
    "pitch": -6.283215,
    "yaw": -0.9672216,
    "roll": -6.283215
  },
  {
    "name": "tree11",
    "x": -3867.225,
    "y": 1076.5079,
    "z": -3865.2139,
    "pitch": 0,
    "yaw": -0.9672216,
    "roll": 0
  },
  {
    "name": "tree11",
    "x": -3885.0847,
    "y": 1076.5079,
    "z": -3862.567,
    "pitch": 0,
    "yaw": -0.9672216,
    "roll": 0
  },
  {
    "name": "tree11",
    "x": -3884.0815,
    "y": 1076.5079,
    "z": -3854.6626,
    "pitch": 0,
    "yaw": -0.9672216,
    "roll": 0
  },
  {
    "name": "tree11",
    "x": -3890.9321,
    "y": 1076.5079,
    "z": -3860.6343,
    "pitch": -6.2832127,
    "yaw": -1.3243492,
    "roll": -6.2832127
  },
  {
    "name": "tree11",
    "x": -3900.1797,
    "y": 1076.5079,
    "z": -3852.9543,
    "pitch": 0,
    "yaw": -1.3243492,
    "roll": 0
  },
  {
    "name": "tree11",
    "x": -3897.8613,
    "y": 1076.5079,
    "z": -3860.7568,
    "pitch": -6.2832103,
    "yaw": -1.7149557,
    "roll": -6.2832103
  },
  {
    "name": "tree11",
    "x": -3905.7788,
    "y": 1076.5079,
    "z": -3852.6514,
    "pitch": 0,
    "yaw": -1.7149557,
    "roll": 0
  },
  {
    "name": "tree11",
    "x": -3912.5,
    "y": 1076.5079,
    "z": -3851.3362,
    "pitch": 0,
    "yaw": -1.7149557,
    "roll": 0
  },
  {
    "name": "tree11",
    "x": -3904.7214,
    "y": 1076.5079,
    "z": -3871.826,
    "pitch": 0,
    "yaw": -1.7149557,
    "roll": 0
  },
  {
    "name": "tree11",
    "x": -3903.347,
    "y": 1076.5079,
    "z": -3863.0032,
    "pitch": 0,
    "yaw": -1.7149557,
    "roll": 0
  },
  {
    "name": "tree11",
    "x": -3910.5544,
    "y": 1076.5079,
    "z": -3869.0737,
    "pitch": 0,
    "yaw": -1.7149557,
    "roll": 0
  },
  {
    "name": "tree11",
    "x": -3917.428,
    "y": 1076.5079,
    "z": -3864.9849,
    "pitch": 0,
    "yaw": -1.7149557,
    "roll": 0
  },
  {
    "name": "tree13",
    "x": -3853.4854,
    "y": 1076.3862,
    "z": -3887.574,
    "pitch": 0,
    "yaw": 0,
    "roll": 0
  },
  {
    "name": "tree13",
    "x": -3860.997,
    "y": 1076.3862,
    "z": -3888.842,
    "pitch": 0,
    "yaw": 0,
    "roll": 0
  },
  {
    "name": "tree13",
    "x": -3866.0046,
    "y": 1076.3862,
    "z": -3883.6777,
    "pitch": 0,
    "yaw": 0,
    "roll": 0
  },
  {
    "name": "tree13",
    "x": -3874.233,
    "y": 1076.3862,
    "z": -3881.8325,
    "pitch": 0,
    "yaw": 0,
    "roll": 0
  },
  {
    "name": "tree13",
    "x": -3865.407,
    "y": 1076.3862,
    "z": -3887.4924,
    "pitch": 0,
    "yaw": 0,
    "roll": 0
  },
  {
    "name": "tree13",
    "x": -3877.3857,
    "y": 1076.3862,
    "z": -3878.3665,
    "pitch": 0,
    "yaw": 0,
    "roll": 0
  },
  {
    "name": "tree13",
    "x": -3870.4868,
    "y": 1076.3862,
    "z": -3873.9807,
    "pitch": 0,
    "yaw": 0,
    "roll": 0
  },
  {
    "name": "tree13",
    "x": -3857.5925,
    "y": 1076.3862,
    "z": -3876.7236,
    "pitch": 0,
    "yaw": 0,
    "roll": 0
  },
  {
    "name": "tree13",
    "x": -3877.951,
    "y": 1076.3862,
    "z": -3865.0312,
    "pitch": 0,
    "yaw": 0,
    "roll": 0
  },
  {
    "name": "tree13",
    "x": -3870.3994,
    "y": 1076.3862,
    "z": -3863.0308,
    "pitch": 0,
    "yaw": 0,
    "roll": 0
  },
  {
    "name": "tree13",
    "x": -3865.6333,
    "y": 1076.3862,
    "z": -3871.842,
    "pitch": 0,
    "yaw": 0,
    "roll": 0
  },
  {
    "name": "tree13",
    "x": -3888.1863,
    "y": 1076.3862,
    "z": -3857.3398,
    "pitch": 0,
    "yaw": 0,
    "roll": 0
  },
  {
    "name": "tree13",
    "x": -3902.4277,
    "y": 1076.3862,
    "z": -3857.72,
    "pitch": 0,
    "yaw": 0,
    "roll": 0
  },
  {
    "name": "tree13",
    "x": -3911.9104,
    "y": 1076.3862,
    "z": -3864.7754,
    "pitch": 0,
    "yaw": 0,
    "roll": 0
  },
  {
    "name": "tree13",
    "x": -3915.477,
    "y": 1076.3862,
    "z": -3858.8457,
    "pitch": -6.2832184,
    "yaw": -1.6479691,
    "roll": -6.2832184
  },
  {
    "name": "tree13",
    "x": -3905.2625,
    "y": 1076.3862,
    "z": -3867.3347,
    "pitch": 0,
    "yaw": -1.6479691,
    "roll": 0
  },
  {
    "name": "tree13",
    "x": -3917.1458,
    "y": 1076.3862,
    "z": -3885.2263,
    "pitch": 0,
    "yaw": -1.6479691,
    "roll": 0
  },
  {
    "name": "tree13",
    "x": -3910.0083,
    "y": 1076.3862,
    "z": -3875.7083,
    "pitch": 0,
    "yaw": -1.6479691,
    "roll": 0
  },
  {
    "name": "tree12",
    "x": -3914.6572,
    "y": 1076.9043,
    "z": -3873.0989,
    "pitch": -6.2832165,
    "yaw": -4.4567842,
    "roll": -6.2832165
  },
  {
    "name": "tree12",
    "x": -3909.064,
    "y": 1076.7305,
    "z": -3881.913,
    "pitch": 0,
    "yaw": 0,
    "roll": 0
  },
  {
    "name": "tree11",
    "x": -3905.6975,
    "y": 1076.3611,
    "z": -3893.5535,
    "pitch": 0,
    "yaw": 0,
    "roll": 0
  },
  {
    "name": "tree11",
    "x": -3913.7493,
    "y": 1076.3611,
    "z": -3890.971,
    "pitch": -6.283224,
    "yaw": 0.85186636,
    "roll": -6.283224
  },
  {
    "name": "tree11",
    "x": -3919.5876,
    "y": 1076.4663,
    "z": -3878.0107,
    "pitch": -6.2833567,
    "yaw": -1.1681384,
    "roll": -6.2833567
  },
  {
    "name": "tree13",
    "x": -3878.519,
    "y": 1076.4531,
    "z": -3882.0312,
    "pitch": -6.2832217,
    "yaw": -0.37203985,
    "roll": -6.2832217
  },
  {
    "name": "tree13",
    "x": -3903.4924,
    "y": 1076.4531,
    "z": -3879.737,
    "pitch": -6.283327,
    "yaw": -0.1488884,
    "roll": -6.283327
  },
  {
    "name": "tree13",
    "x": -3922.7756,
    "y": 1074.1517,
    "z": -3889.6118,
    "pitch": -6.2833004,
    "yaw": -0.84448063,
    "roll": -6.2833004
  },
  {
    "name": "tree13",
    "x": -3922.7852,
    "y": 1073.5088,
    "z": -3854.1958,
    "pitch": 0,
    "yaw": 0,
    "roll": 0
  },
  {
    "name": "tree13",
    "x": -3927.7107,
    "y": 1073.1538,
    "z": -3853.4326,
    "pitch": -6.283234,
    "yaw": -0.7812168,
    "roll": -6.283234
  },
  {
    "name": "tree13",
    "x": -3936.7817,
    "y": 1073.092,
    "z": -3877.2898,
    "pitch": -6.2832184,
    "yaw": -0.41293126,
    "roll": -6.2832184
  },
  {
    "name": "tree13",
    "x": -3933.6973,
    "y": 1073.1893,
    "z": -3883.4822,
    "pitch": -6.419741,
    "yaw": -0.6243159,
    "roll": -6.3810296
  },
  {
    "name": "tree13",
    "x": -3932.284,
    "y": 1073.1893,
    "z": -3887.35,
    "pitch": -6.51599,
    "yaw": -0.6444934,
    "roll": -6.445744
  },
  {
    "name": "tree11",
    "x": -3922.8562,
    "y": 1072.9703,
    "z": -3864.8367,
    "pitch": 0,
    "yaw": 0,
    "roll": 0
  },
  {
    "name": "tree11",
    "x": -3924.242,
    "y": 1074.1422,
    "z": -3870.046,
    "pitch": -6.283295,
    "yaw": -1.1941512,
    "roll": -6.283295
  },
  {
    "name": "tree11",
    "x": -3924.22,
    "y": 1073.4391,
    "z": -3877.1907,
    "pitch": -6.283225,
    "yaw": -0.83332455,
    "roll": -6.283225
  },
  {
    "name": "tree11",
    "x": -3924.076,
    "y": 1073.4391,
    "z": -3882.8655,
    "pitch": -6.2832513,
    "yaw": -0.06702718,
    "roll": -6.2832513
  },
  {
    "name": "tree11",
    "x": -3922.0994,
    "y": 1073.4391,
    "z": -3859.5298,
    "pitch": -6.2832427,
    "yaw": 0.8331925,
    "roll": -6.2832427
  },
  {
    "name": "tree11",
    "x": -3935.2842,
    "y": 1074.1161,
    "z": -3854.8196,
    "pitch": -6.283284,
    "yaw": 1.0563653,
    "roll": -6.283284
  },
  {
    "name": "tree11",
    "x": -3938.1345,
    "y": 1074.1161,
    "z": -3860.565,
    "pitch": -6.2832513,
    "yaw": -4.601865,
    "roll": -6.2832513
  },
  {
    "name": "tree11",
    "x": -3937.935,
    "y": 1074.1161,
    "z": -3866.5427,
    "pitch": -6.2832227,
    "yaw": 1.0526315,
    "roll": -6.2832227
  },
  {
    "name": "tree11",
    "x": -3937.2979,
    "y": 1074.5067,
    "z": -3871.1318,
    "pitch": 0,
    "yaw": 1.0526315,
    "roll": 0
  },
  {
    "name": "tree12",
    "x": -3935.3967,
    "y": 1076.5668,
    "z": -3892.6802,
    "pitch": -6.2833157,
    "yaw": -0.7514855,
    "roll": -6.2833157
  },
  {
    "name": "tree12",
    "x": -3947.1084,
    "y": 1076.2543,
    "z": -3860.692,
    "pitch": -6.2832255,
    "yaw": -0.18977925,
    "roll": -6.2832255
  },
  {
    "name": "tree12",
    "x": -3947.4697,
    "y": 1076.8011,
    "z": -3872.897,
    "pitch": -6.283232,
    "yaw": 0.14500473,
    "roll": -6.283232
  },
  {
    "name": "tree12",
    "x": -3910.0225,
    "y": 1076.6388,
    "z": -3892.466,
    "pitch": -6.2833424,
    "yaw": -4.2595353,
    "roll": -6.2833424
  },
  {
    "name": "tree11",
    "x": -3949.2688,
    "y": 1076.5724,
    "z": -3867.0068,
    "pitch": 0,
    "yaw": 0,
    "roll": 0
  },
  {
    "name": "tree11",
    "x": -3945.475,
    "y": 1076.5724,
    "z": -3879.037,
    "pitch": -6.283225,
    "yaw": 1.0267074,
    "roll": -6.283225
  },
  {
    "name": "tree11",
    "x": -3940.3425,
    "y": 1077.5099,
    "z": -3886.9136,
    "pitch": -6.28336,
    "yaw": -0.8631144,
    "roll": -6.28336
  },
  {
    "name": "tree13",
    "x": -3902.545,
    "y": 1076.5369,
    "z": -3884.571,
    "pitch": 0,
    "yaw": 0,
    "roll": 0
  },
  {
    "name": "tree13",
    "x": -3902.0525,
    "y": 1076.5369,
    "z": -3888.9468,
    "pitch": -6.28331,
    "yaw": -0.78496075,
    "roll": -6.28331
  },
  {
    "name": "tree13",
    "x": -3899.1453,
    "y": 1076.5369,
    "z": -3893.3884,
    "pitch": -6.28321,
    "yaw": -1.3318079,
    "roll": -6.28321
  },
  {
    "name": "tree13",
    "x": -3902.3008,
    "y": 1076.5369,
    "z": -3894.7441,
    "pitch": -6.283219,
    "yaw": -1.927017,
    "roll": -6.283219
  },
  {
    "name": "tree11",
    "x": -3918.0527,
    "y": 1076.5369,
    "z": -3891.2896,
    "pitch": -6.28335,
    "yaw": -1.2425841,
    "roll": -6.28335
  },
  {
    "name": "tree11",
    "x": -3912.0693,
    "y": 1076.5369,
    "z": -3886.2776,
    "pitch": -6.283265,
    "yaw": -2.5408976,
    "roll": -6.283265
  },
  {
    "name": "rd_ro1",
    "x": -3904.1367,
    "y": 1079.3018,
    "z": -3918.784,
    "pitch": -6.2835784,
    "yaw": -0.10429405,
    "roll": -6.2835784
  },
  {
    "name": "rd_sta2",
    "x": -3925.836,
    "y": 1076.3694,
    "z": -3892.571,
    "pitch": -6.283252,
    "yaw": -0.6176761,
    "roll": -6.283252
  },
  {
    "name": "rd_bush1",
    "x": -3911.2407,
    "y": 1079.3452,
    "z": -3909.566,
    "pitch": 0,
    "yaw": 0,
    "roll": 0
  },
  {
    "name": "rd_bush1",
    "x": -3921.0493,
    "y": 1079.3496,
    "z": -3928.6606,
    "pitch": -6.28337,
    "yaw": -1.7484553,
    "roll": -6.28337
  },
  {
    "name": "rd_bush2",
    "x": -3915.2986,
    "y": 1079.5015,
    "z": -3920.9026,
    "pitch": -6.283351,
    "yaw": -0.66965944,
    "roll": -6.283351
  },
  {
    "name": "tree_02m",
    "x": -3913.0447,
    "y": 1079.32,
    "z": -3931.6748,
    "pitch": -6.230526,
    "yaw": -1.2090462,
    "roll": -6.1444297
  },
  {
    "name": "tree_d03",
    "x": -3920.4016,
    "y": 1079.3555,
    "z": -3909.7068,
    "pitch": -6.286414,
    "yaw": -1.8121958,
    "roll": -6.178205
  },
  {
    "name": "tree_02m",
    "x": -3895.2415,
    "y": 1079.3129,
    "z": -3911.3257,
    "pitch": -6.417301,
    "yaw": -7.634965E-05,
    "roll": -6.2833905
  },
  {
    "name": "tree_02m",
    "x": -3897.9875,
    "y": 1079.265,
    "z": -3913.9746,
    "pitch": -6.2396307,
    "yaw": -1.8455412,
    "roll": -6.4372816
  },
  {
    "name": "tree_02m",
    "x": -3901.327,
    "y": 1079.2999,
    "z": -3918.3706,
    "pitch": -6.0648117,
    "yaw": -3.2778409,
    "roll": -6.3760858
  },
  {
    "name": "tree11",
    "x": -3895.7698,
    "y": 1079.508,
    "z": -3919.7769,
    "pitch": -6.3651853,
    "yaw": -6.45081E-05,
    "roll": -6.2833457
  },
  {
    "name": "tree13",
    "x": -3900.956,
    "y": 1079.4099,
    "z": -3931.913,
    "pitch": -6.3269258,
    "yaw": -1.0843794,
    "roll": -6.3655386
  },
  {
    "name": "rd_bush3",
    "x": -3901.557,
    "y": 1079.4222,
    "z": -3924.5051,
    "pitch": -6.28858,
    "yaw": -3.3520107,
    "roll": -6.278092
  },
  {
    "name": "tree1_1",
    "x": -3944.01,
    "y": 1079.3285,
    "z": -3957.0742,
    "pitch": -6.231961,
    "yaw": -1.3334937,
    "roll": -6.0738187
  },
  {
    "name": "tree_01m",
    "x": -3958.762,
    "y": 1079.2219,
    "z": -3941.62,
    "pitch": -6.296378,
    "yaw": -1.4740572,
    "roll": -6.4166517
  },
  {
    "name": "rd_bush1",
    "x": -3948.2222,
    "y": 1079.2682,
    "z": -3941.856,
    "pitch": -6.240767,
    "yaw": -0.97995824,
    "roll": -6.2252426
  },
  {
    "name": "rd_bush1",
    "x": -3966.1448,
    "y": 1079.3428,
    "z": -3889.7935,
    "pitch": -6.2832894,
    "yaw": -1.2797142,
    "roll": -6.2832894
  },
  {
    "name": "rd_bush1",
    "x": -3969.676,
    "y": 1079.0714,
    "z": -3839.8452,
    "pitch": -6.2832956,
    "yaw": -2.481278,
    "roll": -6.2832956
  },
  {
    "name": "rd_bush1",
    "x": -3911.584,
    "y": 1078.9905,
    "z": -3826.0525,
    "pitch": -6.311462,
    "yaw": -2.2501967,
    "roll": -6.2486777
  },
  {
    "name": "rd_bush1",
    "x": -3837.553,
    "y": 1079.2646,
    "z": -3939.3997,
    "pitch": -6.2833138,
    "yaw": -1.7893578,
    "roll": -6.2833138
  },
  {
    "name": "rd_bush2",
    "x": -3836.572,
    "y": 1079.1145,
    "z": -3871.5981,
    "pitch": 0,
    "yaw": 0,
    "roll": 0
  },
  {
    "name": "rd_bush2",
    "x": -3859.5198,
    "y": 1079.1062,
    "z": -3843.1404,
    "pitch": -6.2833033,
    "yaw": -1.7186748,
    "roll": -6.2833033
  },
  {
    "name": "rd_bush3",
    "x": -3926.2717,
    "y": 1079.0621,
    "z": -3839.805,
    "pitch": 0,
    "yaw": 0,
    "roll": 0
  },
  {
    "name": "tree_d02",
    "x": -3969.2668,
    "y": 1079.1278,
    "z": -3865.2021,
    "pitch": -6.328408,
    "yaw": -0.9202172,
    "roll": -6.3424754
  },
  {
    "name": "tree_d02",
    "x": -3883.2449,
    "y": 1079.016,
    "z": -3834.2603,
    "pitch": -6.335685,
    "yaw": -3.7139542,
    "roll": -6.3539987
  },
  {
    "name": "tree_01m",
    "x": -3962.2954,
    "y": 1079.269,
    "z": -3916.226,
    "pitch": -6.238484,
    "yaw": -1.9205455,
    "roll": -6.405597
  },
  {
    "name": "tree_02m",
    "x": -3946.9119,
    "y": 1079.2961,
    "z": -3925.1333,
    "pitch": -6.3053412,
    "yaw": -1.3964128,
    "roll": -6.407832
  },
  {
    "name": "tree_02m",
    "x": -3938.1948,
    "y": 1079.3578,
    "z": -3913.075,
    "pitch": -6.2508917,
    "yaw": -1.2291274,
    "roll": -6.1922755
  },
  {
    "name": "tree1_1",
    "x": -3824.2402,
    "y": 1079.4564,
    "z": -3895.6035,
    "pitch": -6.241353,
    "yaw": -1.3543743,
    "roll": -6.0945196
  },
  {
    "name": "tree4_1",
    "x": -3833.9338,
    "y": 1078.3435,
    "z": -3830.4768,
    "pitch": -6.2327156,
    "yaw": -0.22730875,
    "roll": -6.2717266
  },
  {
    "name": "tree4_3",
    "x": -3860.455,
    "y": 1082.0869,
    "z": -3824.0571,
    "pitch": 0,
    "yaw": 0,
    "roll": 0
  },
  {
    "name": "tree4_5",
    "x": -3853.875,
    "y": 1079.3027,
    "z": -3834.2588,
    "pitch": 0,
    "yaw": 0,
    "roll": 0
  },
  {
    "name": "tree4_5",
    "x": -3868.6997,
    "y": 1079.4862,
    "z": -3845.677,
    "pitch": -6.282219,
    "yaw": -1.5624983,
    "roll": -6.149422
  },
  {
    "name": "tree4_6",
    "x": -3843.163,
    "y": 1078.9476,
    "z": -3848.3179,
    "pitch": -6.2943177,
    "yaw": -1.4364138,
    "roll": -6.3644276
  },
  {
    "name": "tree4_6",
    "x": -3843.2964,
    "y": 1079.4456,
    "z": -3911.3743,
    "pitch": -6.3415027,
    "yaw": -0.60384727,
    "roll": -6.323398
  },
  {
    "name": "tree4_6",
    "x": -3826.0532,
    "y": 1079.2446,
    "z": -3916.5903,
    "pitch": -6.268284,
    "yaw": -1.414363,
    "roll": -6.187861
  },
  {
    "name": "tree4_6",
    "x": -3821.957,
    "y": 1079.1809,
    "z": -3880.776,
    "pitch": -6.232253,
    "yaw": -2.3759599,
    "roll": -6.184188
  },
  {
    "name": "tree4_5",
    "x": -3835.162,
    "y": 1079.4661,
    "z": -3898.461,
    "pitch": -6.3604126,
    "yaw": -1.0580622,
    "roll": -6.4193006
  },
  {
    "name": "tree4_4",
    "x": -3842.8564,
    "y": 1079.3313,
    "z": -3885.9463,
    "pitch": -6.209041,
    "yaw": -2.2171986,
    "roll": -6.28343
  },
  {
    "name": "rd_bush2",
    "x": -3874.1265,
    "y": 1079.4637,
    "z": -3938.931,
    "pitch": -6.283274,
    "yaw": -1.3801454,
    "roll": -6.283274
  },
  {
    "name": "rd_bush3",
    "x": -3863.678,
    "y": 1079.3744,
    "z": -3918.711,
    "pitch": -6.2833266,
    "yaw": -1.8898035,
    "roll": -6.2833266
  },
  {
    "name": "tree_05",
    "x": -3853.5642,
    "y": 1079.6796,
    "z": -3937.6646,
    "pitch": -6.2832837,
    "yaw": -1.8451492,
    "roll": -6.2832837
  },
  {
    "name": "tree11",
    "x": -3944.894,
    "y": 1079.8293,
    "z": -3822.5625,
    "pitch": -6.3335223,
    "yaw": -1.1373726,
    "roll": -6.3913174
  },
  {
    "name": "tree11",
    "x": -3957.3762,
    "y": 1079.375,
    "z": -3850.3613,
    "pitch": -6.2907996,
    "yaw": -1.5221004,
    "roll": -6.4356513
  },
  {
    "name": "tree11",
    "x": -3949.8213,
    "y": 1079.5537,
    "z": -3900.1082,
    "pitch": -6.186875,
    "yaw": -0.79715186,
    "roll": -6.185049
  },
  {
    "name": "tree12",
    "x": -3939.6458,
    "y": 1079.6248,
    "z": -3929.3293,
    "pitch": -6.27458,
    "yaw": -1.5072356,
    "roll": -6.146017
  },
  {
    "name": "tree12",
    "x": -3970.8784,
    "y": 1079.9214,
    "z": -3900.4644,
    "pitch": -6.2502794,
    "yaw": -3.383109,
    "roll": -6.417105
  },
  {
    "name": "tree12",
    "x": -3878.1372,
    "y": 1079.9305,
    "z": -3961.2744,
    "pitch": -6.476773,
    "yaw": -2.6117628,
    "roll": -6.1712565
  },
  {
    "name": "tree13",
    "x": -3924.3513,
    "y": 1079.8345,
    "z": -3942.2224,
    "pitch": -6.1845994,
    "yaw": -2.1010487,
    "roll": -6.4499545
  },
  {
    "name": "tree13",
    "x": -3918.8523,
    "y": 1079.6813,
    "z": -3963.4194,
    "pitch": -6.328784,
    "yaw": -1.8565335,
    "roll": -6.1299195
  },
  {
    "name": "tree4_6",
    "x": -3928.6729,
    "y": 1079.4744,
    "z": -3962.9194,
    "pitch": -6.2656674,
    "yaw": -1.7288691,
    "roll": -6.3935084
  },
  {
    "name": "tree4_6",
    "x": -3931.4324,
    "y": 1079.4268,
    "z": -3946.4316,
    "pitch": -6.364544,
    "yaw": -0.97958297,
    "roll": -6.403607
  },
  {
    "name": "tree_01m",
    "x": -3828.9717,
    "y": 1079.144,
    "z": -3929.0334,
    "pitch": -6.222964,
    "yaw": -2.5253966,
    "roll": -6.0573387
  },
  {
    "name": "tree_01m",
    "x": -3956.5405,
    "y": 1079.0487,
    "z": -3830.889,
    "pitch": -6.283339,
    "yaw": -2.7193725,
    "roll": -6.283339
  },
  {
    "name": "tree11",
    "x": -3894.8533,
    "y": 1079.8599,
    "z": -3929.9272,
    "pitch": 0,
    "yaw": 0,
    "roll": 0
  },
  {
    "name": "tree12",
    "x": -3884.6575,
    "y": 1080.2502,
    "z": -3926.471,
    "pitch": 0,
    "yaw": 0,
    "roll": 0
  },
  {
    "name": "tree12",
    "x": -3859.8413,
    "y": 1079.8596,
    "z": -3918.1282,
    "pitch": 0,
    "yaw": 0,
    "roll": 0
  },
  {
    "name": "char19",
    "x": -1094.8451,
    "y": 1100.9375,
    "z": -3892.9407,
    "pitch": -6.283341,
    "yaw": -4.2110834,
    "roll": -6.283341
  },
  {
    "name": "grass1_11",
    "x": -3860.4001,
    "y": 1079.2067,
    "z": -3918.0796,
    "pitch": -6.2572947,
    "yaw": 0.49858433,
    "roll": -6.2976627
  },
  {
    "name": "grass1_12",
    "x": -3854.022,
    "y": 1079.2899,
    "z": -3937.089,
    "pitch": -6.2834163,
    "yaw": -1.8563588,
    "roll": -6.2834163
  },
  {
    "name": "grass1_13",
    "x": -3828.933,
    "y": 1079.2552,
    "z": -3928.944,
    "pitch": 0,
    "yaw": 0,
    "roll": 0
  },
  {
    "name": "grass1_21",
    "x": -3836.5786,
    "y": 1078.9626,
    "z": -3874.0674,
    "pitch": 0,
    "yaw": 0,
    "roll": 0
  },
  {
    "name": "grass1_22",
    "x": -3842.0066,
    "y": 1079.1998,
    "z": -3912.1602,
    "pitch": 0,
    "yaw": 0,
    "roll": 0
  },
  {
    "name": "grass1_31",
    "x": -3842.2292,
    "y": 1078.9583,
    "z": -3885.642,
    "pitch": 0,
    "yaw": 0,
    "roll": 0
  },
  {
    "name": "grass1_32",
    "x": -3825.8901,
    "y": 1078.8574,
    "z": -3895.002,
    "pitch": 0,
    "yaw": 0,
    "roll": 0
  },
  {
    "name": "grass1_11",
    "x": -3826.3047,
    "y": 1079.1056,
    "z": -3893.833,
    "pitch": 0,
    "yaw": 0,
    "roll": 0
  },
  {
    "name": "grass1_11",
    "x": -3944.2727,
    "y": 1079.563,
    "z": -3822.6025,
    "pitch": 0,
    "yaw": 0,
    "roll": 0
  },
  {
    "name": "grass1_12",
    "x": -3956.557,
    "y": 1078.8481,
    "z": -3830.6492,
    "pitch": 0,
    "yaw": 0,
    "roll": 0
  },
  {
    "name": "grass1_12",
    "x": -3957.1804,
    "y": 1078.8845,
    "z": -3834.1821,
    "pitch": -6.2832494,
    "yaw": 0.3980185,
    "roll": -6.2832494
  },
  {
    "name": "grass1_11",
    "x": -3956.3818,
    "y": 1078.9943,
    "z": -3849.6096,
    "pitch": 0,
    "yaw": 0,
    "roll": 0
  },
  {
    "name": "grass1_11",
    "x": -3955.9836,
    "y": 1079.1248,
    "z": -3852.689,
    "pitch": 0,
    "yaw": 0,
    "roll": 0
  },
  {
    "name": "grass1_13",
    "x": -3949.543,
    "y": 1079.2341,
    "z": -3899.6597,
    "pitch": 0,
    "yaw": 0,
    "roll": 0
  },
  {
    "name": "grass1_13",
    "x": -3950.872,
    "y": 1079.2739,
    "z": -3901.6797,
    "pitch": 0,
    "yaw": 0,
    "roll": 0
  },
  {
    "name": "grass1_12",
    "x": -3969.446,
    "y": 1079.1147,
    "z": -3864.8953,
    "pitch": 0,
    "yaw": 0,
    "roll": 0
  },
  {
    "name": "grass1_12",
    "x": -3967.9988,
    "y": 1079.0297,
    "z": -3862.1843,
    "pitch": 0,
    "yaw": 0,
    "roll": 0
  },
  {
    "name": "grass1_11",
    "x": -3960.622,
    "y": 1079.2769,
    "z": -3916.5476,
    "pitch": 0,
    "yaw": 0,
    "roll": 0
  },
  {
    "name": "grass1_12",
    "x": -3946.5386,
    "y": 1079.1837,
    "z": -3926.4634,
    "pitch": 0,
    "yaw": 0,
    "roll": 0
  },
  {
    "name": "grass1_21",
    "x": -3941.304,
    "y": 1079.4055,
    "z": -3924.444,
    "pitch": 0,
    "yaw": 0,
    "roll": 0
  },
  {
    "name": "grass1_11",
    "x": -3939.7922,
    "y": 1079.2281,
    "z": -3929.8538,
    "pitch": 0,
    "yaw": 0,
    "roll": 0
  },
  {
    "name": "grass1_11",
    "x": -3942.742,
    "y": 1079.2336,
    "z": -3928.9453,
    "pitch": -6.283273,
    "yaw": 1.0973705,
    "roll": -6.283273
  },
  {
    "name": "grass1_13",
    "x": -3957.5967,
    "y": 1078.6095,
    "z": -3942.8198,
    "pitch": -6.2201896,
    "yaw": -7.273654E-05,
    "roll": -6.2834272
  },
  {
    "name": "grass1_13",
    "x": -3960.341,
    "y": 1079.0367,
    "z": -3941.0212,
    "pitch": 0,
    "yaw": 0,
    "roll": 0
  },
  {
    "name": "grass1_13",
    "x": -3970.6897,
    "y": 1079.236,
    "z": -3900.5022,
    "pitch": 0,
    "yaw": 0,
    "roll": 0
  },
  {
    "name": "grass1_31",
    "x": -3943.5674,
    "y": 1079.1348,
    "z": -3952.6748,
    "pitch": -6.3455615,
    "yaw": -0.033853017,
    "roll": -6.2243333
  },
  {
    "name": "grass1_12",
    "x": -3947.4324,
    "y": 1078.2892,
    "z": -3955.4856,
    "pitch": -6.3829536,
    "yaw": 0.02713152,
    "roll": -6.1984663
  },
  {
    "name": "grass1_12",
    "x": -3941.6328,
    "y": 1079.1663,
    "z": -3958.9277,
    "pitch": 0,
    "yaw": 0,
    "roll": 0
  },
  {
    "name": "grass1_12",
    "x": -3928.8362,
    "y": 1079.2728,
    "z": -3962.6992,
    "pitch": -6.2832346,
    "yaw": 0.14134319,
    "roll": -6.2832346
  },
  {
    "name": "grass1_12",
    "x": -3919.4324,
    "y": 1079.2219,
    "z": -3963.1726,
    "pitch": 0,
    "yaw": 0,
    "roll": 0
  },
  {
    "name": "grass1_13",
    "x": -3931.215,
    "y": 1079.2676,
    "z": -3946.1128,
    "pitch": 0,
    "yaw": 0,
    "roll": 0
  },
  {
    "name": "grass1_21",
    "x": -3912.8115,
    "y": 1079.2739,
    "z": -3933.2976,
    "pitch": 0,
    "yaw": 0,
    "roll": 0
  },
  {
    "name": "grass1_21",
    "x": -3897.629,
    "y": 1079.2284,
    "z": -3931.0603,
    "pitch": 0,
    "yaw": 0,
    "roll": 0
  },
  {
    "name": "grass1_12",
    "x": -3884.9678,
    "y": 1079.2289,
    "z": -3926.4116,
    "pitch": 0,
    "yaw": 0,
    "roll": 0
  },
  {
    "name": "grass1_11",
    "x": -3878.1055,
    "y": 1079.245,
    "z": -3961.0151,
    "pitch": 0,
    "yaw": 0,
    "roll": 0
  },
  {
    "name": "grass1_11",
    "x": -3854.8325,
    "y": 1079.325,
    "z": -3939.284,
    "pitch": 0,
    "yaw": 0,
    "roll": 0
  },
  {
    "name": "grass1_11",
    "x": -3862.7095,
    "y": 1076.3077,
    "z": -3897.231,
    "pitch": 0,
    "yaw": 0,
    "roll": 0
  },
  {
    "name": "grass1_11",
    "x": -3865.021,
    "y": 1076.2743,
    "z": -3892.7725,
    "pitch": -6.2832546,
    "yaw": 0.40545636,
    "roll": -6.2832546
  },
  {
    "name": "grass1_11",
    "x": -3861.2712,
    "y": 1076.2223,
    "z": -3892.508,
    "pitch": 0,
    "yaw": 0,
    "roll": 0
  },
  {
    "name": "grass1_11",
    "x": -3864.908,
    "y": 1076.1752,
    "z": -3888.042,
    "pitch": 0,
    "yaw": 0,
    "roll": 0
  },
  {
    "name": "grass1_11",
    "x": -3865.5156,
    "y": 1076.1793,
    "z": -3885.1826,
    "pitch": 0,
    "yaw": 0,
    "roll": 0
  },
  {
    "name": "grass1_11",
    "x": -3857.3992,
    "y": 1076.2599,
    "z": -3891.4592,
    "pitch": 0,
    "yaw": 0,
    "roll": 0
  },
  {
    "name": "grass1_11",
    "x": -3860.5474,
    "y": 1076.242,
    "z": -3887.7837,
    "pitch": -6.2833705,
    "yaw": 0.6732588,
    "roll": -6.2833705
  },
  {
    "name": "grass1_11",
    "x": -3854.5498,
    "y": 1076.2688,
    "z": -3888.0713,
    "pitch": 0,
    "yaw": 0,
    "roll": 0
  },
  {
    "name": "grass1_11",
    "x": -3859.983,
    "y": 1076.2958,
    "z": -3882.5823,
    "pitch": -6.2832823,
    "yaw": 0.55796665,
    "roll": -6.2832823
  },
  {
    "name": "grass1_12",
    "x": -3870.494,
    "y": 1076.1461,
    "z": -3877.4902,
    "pitch": 0,
    "yaw": 0,
    "roll": 0
  },
  {
    "name": "grass1_12",
    "x": -3873.6523,
    "y": 1076.1487,
    "z": -3870.1614,
    "pitch": -6.2832775,
    "yaw": 0.7476882,
    "roll": -6.2832775
  },
  {
    "name": "grass1_12",
    "x": -3865.7896,
    "y": 1076.0756,
    "z": -3871.4175,
    "pitch": -6.2832513,
    "yaw": 0.5282171,
    "roll": -6.2832513
  },
  {
    "name": "grass1_12",
    "x": -3868.6152,
    "y": 1075.7991,
    "z": -3864.5322,
    "pitch": 0,
    "yaw": 0,
    "roll": 0
  },
  {
    "name": "grass1_12",
    "x": -3861.3171,
    "y": 1075.8479,
    "z": -3870.6162,
    "pitch": -6.41638,
    "yaw": -0.017179618,
    "roll": -6.3628135
  },
  {
    "name": "grass1_12",
    "x": -3877.9104,
    "y": 1076.1761,
    "z": -3864.7007,
    "pitch": 0,
    "yaw": 0,
    "roll": 0
  },
  {
    "name": "grass1_12",
    "x": -3876.6064,
    "y": 1075.9176,
    "z": -3857.693,
    "pitch": 0,
    "yaw": 0,
    "roll": 0
  },
  {
    "name": "grass1_12",
    "x": -3884.4712,
    "y": 1075.8097,
    "z": -3854.4868,
    "pitch": -6.3391924,
    "yaw": -8.002185E-05,
    "roll": -6.2833934
  },
  {
    "name": "grass1_12",
    "x": -3887.8354,
    "y": 1076.1467,
    "z": -3860.9116,
    "pitch": 0,
    "yaw": 0,
    "roll": 0
  },
  {
    "name": "grass1_12",
    "x": -3902.6345,
    "y": 1076.2008,
    "z": -3861.245,
    "pitch": 0,
    "yaw": 0,
    "roll": 0
  },
  {
    "name": "grass1_12",
    "x": -3898.34,
    "y": 1076.0061,
    "z": -3853.3098,
    "pitch": 0,
    "yaw": 0,
    "roll": 0
  },
  {
    "name": "grass1_13",
    "x": -3911.1033,
    "y": 1076.1871,
    "z": -3869.3162,
    "pitch": 0,
    "yaw": 0,
    "roll": 0
  },
  {
    "name": "grass1_13",
    "x": -3912.8757,
    "y": 1076.1929,
    "z": -3864.9663,
    "pitch": 0,
    "yaw": 0,
    "roll": 0
  },
  {
    "name": "grass1_13",
    "x": -3916.7556,
    "y": 1076.2164,
    "z": -3864.5513,
    "pitch": 0,
    "yaw": 0,
    "roll": 0
  },
  {
    "name": "grass1_13",
    "x": -3914.8206,
    "y": 1076.1941,
    "z": -3872.8206,
    "pitch": 0,
    "yaw": 0,
    "roll": 0
  },
  {
    "name": "grass1_13",
    "x": -3918.4634,
    "y": 1076.3177,
    "z": -3879.951,
    "pitch": 0,
    "yaw": 0,
    "roll": 0
  },
  {
    "name": "grass1_13",
    "x": -3903.814,
    "y": 1076.2019,
    "z": -3880.4165,
    "pitch": 0,
    "yaw": 0,
    "roll": 0
  },
  {
    "name": "grass1_13",
    "x": -3904.2378,
    "y": 1076.2267,
    "z": -3888.602,
    "pitch": 0,
    "yaw": 0,
    "roll": 0
  },
  {
    "name": "grass1_13",
    "x": -3903.4775,
    "y": 1076.201,
    "z": -3884.0107,
    "pitch": 0,
    "yaw": 0,
    "roll": 0
  },
  {
    "name": "grass1_13",
    "x": -3908.7366,
    "y": 1076.1746,
    "z": -3881.7136,
    "pitch": 0,
    "yaw": 0,
    "roll": 0
  },
  {
    "name": "grass1_13",
    "x": -3906.2126,
    "y": 1076.2396,
    "z": -3883.9072,
    "pitch": -6.2832875,
    "yaw": 1.2350079,
    "roll": -6.2832875
  },
  {
    "name": "grass1_13",
    "x": -3916.1714,
    "y": 1076.2234,
    "z": -3885.0166,
    "pitch": 0,
    "yaw": 0,
    "roll": 0
  },
  {
    "name": "grass1_13",
    "x": -3910.9312,
    "y": 1076.182,
    "z": -3887.1133,
    "pitch": -6.283269,
    "yaw": 0.9746119,
    "roll": -6.283269
  },
  {
    "name": "grass1_13",
    "x": -3917.5095,
    "y": 1076.1869,
    "z": -3890.9587,
    "pitch": 0,
    "yaw": 0,
    "roll": 0
  },
  {
    "name": "grass1_13",
    "x": -3902.1506,
    "y": 1076.3153,
    "z": -3895.281,
    "pitch": 0,
    "yaw": 0,
    "roll": 0
  },
  {
    "name": "grass1_13",
    "x": -3924.4143,
    "y": 1072.8542,
    "z": -3883.1204,
    "pitch": 0,
    "yaw": 0,
    "roll": 0
  },
  {
    "name": "grass1_11",
    "x": -3932.6218,
    "y": 1072.9503,
    "z": -3883.0764,
    "pitch": 0,
    "yaw": 0,
    "roll": 0
  },
  {
    "name": "grass1_11",
    "x": -3931.6357,
    "y": 1073.2236,
    "z": -3886.9739,
    "pitch": -6.283293,
    "yaw": 0.13016361,
    "roll": -6.283293
  },
  {
    "name": "grass1_12",
    "x": -3934.818,
    "y": 1072.8115,
    "z": -3876.741,
    "pitch": -6.283413,
    "yaw": 0.08176239,
    "roll": -6.283413
  },
  {
    "name": "grass1_12",
    "x": -3932.1958,
    "y": 1072.8531,
    "z": -3870.5457,
    "pitch": 0,
    "yaw": 0,
    "roll": 0
  },
  {
    "name": "grass1_12",
    "x": -3923.442,
    "y": 1072.8335,
    "z": -3858.7595,
    "pitch": 0,
    "yaw": 0,
    "roll": 0
  },
  {
    "name": "grass1_12",
    "x": -3928.449,
    "y": 1072.7292,
    "z": -3854.9048,
    "pitch": -6.409566,
    "yaw": -4.6523976,
    "roll": -6.364891
  },
  {
    "name": "grass1_22",
    "x": -3932.2644,
    "y": 1072.8113,
    "z": -3861.84,
    "pitch": 0,
    "yaw": 0,
    "roll": 0
  },
  {
    "name": "grass1_22",
    "x": -3893.824,
    "y": 1079.2396,
    "z": -3917.602,
    "pitch": 0,
    "yaw": 0,
    "roll": 0
  },
  {
    "name": "grass1_31",
    "x": -3892.598,
    "y": 1079.3192,
    "z": -3915.4636,
    "pitch": -6.2832375,
    "yaw": 0.5356624,
    "roll": -6.2832375
  }
]