[
  {
    "name": "empty",
    "x": 2490.772,
    "y": 159.39604,
    "z": 1346.7313,
    "pitch": 0,
    "yaw": 0,
    "roll": 0
  },
  {
    "name": "empty",
    "x": -2594.0247,
    "y": -111.35133,
    "z": -326.32507,
    "pitch": 0,
    "yaw": 0,
    "roll": 0
  },
  {
    "name": "empty",
    "x": -1099.7812,
    "y": 1699.9144,
    "z": -3298.5186,
    "pitch": 0,
    "yaw": 0,
    "roll": 0
  },
  {
    "name": "empty",
    "x": -611.60187,
    "y": -107.419266,
    "z": -290.5056,
    "pitch": 0,
    "yaw": 0,
    "roll": 0
  },
  {
    "name": "empty",
    "x": -699.7812,
    "y": 1699.9144,
    "z": -3298.5186,
    "pitch": 0,
    "yaw": 0,
    "roll": 0
  },
  {
    "name": "empty",
    "x": -1403.4054,
    "y": -106.96584,
    "z": 687.83124,
    "pitch": 0,
    "yaw": 0,
    "roll": 0
  },
  {
    "name": "empty",
    "x": -900,
    "y": 1700,
    "z": -3298.5,
    "pitch": 0,
    "yaw": 0,
    "roll": 0
  },
  {
    "name": "lbg_1a",
    "x": -1100,
    "y": 1700,
    "z": -3300,
    "pitch": 0,
    "yaw": 0,
    "roll": 0
  },
  {
    "name": "lbg_4b",
    "x": -1100,
    "y": 1700,
    "z": -3315,
    "pitch": 0,
    "yaw": 0,
    "roll": 0
  },
  {
    "name": "lbg_4a",
    "x": -1100,
    "y": 1700,
    "z": -3330,
    "pitch": 0,
    "yaw": 0,
    "roll": 0
  },
  {
    "name": "lbg_4c",
    "x": -1100,
    "y": 1700,
    "z": -3345,
    "pitch": 0,
    "yaw": 0,
    "roll": 0
  },
  {
    "name": "lbg_4d",
    "x": -1085,
    "y": 1700,
    "z": -3345,
    "pitch": 0,
    "yaw": 0,
    "roll": 0
  },
  {
    "name": "lbg_2a",
    "x": -1085,
    "y": 1700,
    "z": -3360,
    "pitch": 0,
    "yaw": 0,
    "roll": 0
  },
  {
    "name": "lbg_2i",
    "x": -1085,
    "y": 1700,
    "z": -3330,
    "pitch": 0,
    "yaw": 3.1415927,
    "roll": 0
  },
  {
    "name": "lbg_3e",
    "x": -1040,
    "y": 1700,
    "z": -3375,
    "pitch": 0,
    "yaw": 0,
    "roll": 0
  },
  {
    "name": "lbg_2c",
    "x": -1055,
    "y": 1700,
    "z": -3390,
    "pitch": 0,
    "yaw": 4.712389,
    "roll": 0
  },
  {
    "name": "lbg_2i",
    "x": -1040,
    "y": 1700,
    "z": -3390,
    "pitch": 0,
    "yaw": 1.5707964,
    "roll": 0
  },
  {
    "name": "lbg_2e",
    "x": -1070,
    "y": 1700,
    "z": -3390,
    "pitch": 0,
    "yaw": 1.5707964,
    "roll": 0
  },
  {
    "name": "lbg_2e",
    "x": -1085,
    "y": 1700,
    "z": -3390,
    "pitch": 0,
    "yaw": 4.712389,
    "roll": 0
  },
  {
    "name": "lbg_2f",
    "x": -1100,
    "y": 1700,
    "z": -3390,
    "pitch": 0,
    "yaw": 4.712389,
    "roll": 0
  },
  {
    "name": "lbg_2a",
    "x": -1115,
    "y": 1700,
    "z": -3390,
    "pitch": 0,
    "yaw": 4.712389,
    "roll": 0
  },
  {
    "name": "lbg_2g",
    "x": -1130,
    "y": 1700,
    "z": -3390,
    "pitch": 0,
    "yaw": 0,
    "roll": 0
  },
  {
    "name": "lbg_2k",
    "x": -1130,
    "y": 1700,
    "z": -3375,
    "pitch": 0,
    "yaw": 0,
    "roll": 0
  },
  {
    "name": "lbg_2e",
    "x": -1115,
    "y": 1700,
    "z": -3375,
    "pitch": 0,
    "yaw": 1.5707964,
    "roll": 0
  },
  {
    "name": "lbg_2b",
    "x": -1100,
    "y": 1700,
    "z": -3375,
    "pitch": 0,
    "yaw": 1.5707964,
    "roll": 0
  },
  {
    "name": "lbg_2h",
    "x": -1085,
    "y": 1700,
    "z": -3375,
    "pitch": 0,
    "yaw": 1.5707964,
    "roll": 0
  },
  {
    "name": "lbg_1f",
    "x": -1100,
    "y": 1700,
    "z": -3360,
    "pitch": 0,
    "yaw": 3.1415927,
    "roll": 0
  },
  {
    "name": "lbg_3f",
    "x": -1025,
    "y": 1700,
    "z": -3375,
    "pitch": 0,
    "yaw": 4.712389,
    "roll": 0
  },
  {
    "name": "lbg_1f",
    "x": -1055,
    "y": 1700,
    "z": -3375,
    "pitch": 0,
    "yaw": 1.5707964,
    "roll": 0
  },
  {
    "name": "LBG_1G",
    "x": -1025,
    "y": 1700,
    "z": -3360,
    "pitch": 0,
    "yaw": 0,
    "roll": 0
  },
  {
    "name": "lbg_1h",
    "x": -1025,
    "y": 1700,
    "z": -3390,
    "pitch": 0,
    "yaw": 1.5707964,
    "roll": 0
  },
  {
    "name": "lbg_1f",
    "x": -1070,
    "y": 1700,
    "z": -3345,
    "pitch": 0,
    "yaw": 4.712389,
    "roll": 0
  },
  {
    "name": "lbg_1b",
    "x": -1115,
    "y": 1700,
    "z": -3345,
    "pitch": 0,
    "yaw": 0,
    "roll": 0
  },
  {
    "name": "lbg_2g",
    "x": -1115,
    "y": 1700,
    "z": -3330,
    "pitch": 0,
    "yaw": 0,
    "roll": 0
  },
  {
    "name": "lbg_2j",
    "x": -1115,
    "y": 1700,
    "z": -3315,
    "pitch": 0,
    "yaw": 0,
    "roll": 0
  },
  {
    "name": "LBG_1G",
    "x": -1085,
    "y": 1700,
    "z": -3315,
    "pitch": 0,
    "yaw": 4.712389,
    "roll": 0
  },
  {
    "name": "lbg_2e",
    "x": -900,
    "y": 1700,
    "z": -3300,
    "pitch": 0,
    "yaw": 0,
    "roll": 0
  },
  {
    "name": "lbg_2d",
    "x": -900,
    "y": 1700,
    "z": -3315,
    "pitch": 0,
    "yaw": 0,
    "roll": 0
  },
  {
    "name": "lbg_2a",
    "x": -900,
    "y": 1700,
    "z": -3330,
    "pitch": 0,
    "yaw": 0,
    "roll": 0
  },
  {
    "name": "lbg_2f",
    "x": -900,
    "y": 1700,
    "z": -3345,
    "pitch": 0,
    "yaw": 0,
    "roll": 0
  },
  {
    "name": "lbg_2h",
    "x": -900,
    "y": 1700,
    "z": -3360,
    "pitch": 0,
    "yaw": 1.5707964,
    "roll": 0
  },
  {
    "name": "lbg_2c",
    "x": -915,
    "y": 1700,
    "z": -3360,
    "pitch": 0,
    "yaw": 1.5707964,
    "roll": 0
  },
  {
    "name": "lbg_3d",
    "x": -930,
    "y": 1700,
    "z": -3360,
    "pitch": 0,
    "yaw": 3.1415927,
    "roll": 0
  },
  {
    "name": "lbg_1b",
    "x": -945,
    "y": 1700,
    "z": -3360,
    "pitch": 0,
    "yaw": 0,
    "roll": 0
  },
  {
    "name": "lbg_2e",
    "x": -930,
    "y": 1700,
    "z": -3345,
    "pitch": 0,
    "yaw": 3.1415927,
    "roll": 0
  },
  {
    "name": "lbg_2c",
    "x": -930,
    "y": 1700,
    "z": -3330,
    "pitch": 0,
    "yaw": 3.1415927,
    "roll": 0
  },
  {
    "name": "lbg_2f",
    "x": -930,
    "y": 1700,
    "z": -3315,
    "pitch": 0,
    "yaw": 3.1415927,
    "roll": 0
  },
  {
    "name": "lbg_2k",
    "x": -930,
    "y": 1700,
    "z": -3300,
    "pitch": 0,
    "yaw": 4.712389,
    "roll": 0
  },
  {
    "name": "lbg_2b",
    "x": -945,
    "y": 1700,
    "z": -3300,
    "pitch": 0,
    "yaw": 4.712389,
    "roll": 0
  },
  {
    "name": "lbg_2d",
    "x": -960,
    "y": 1700,
    "z": -3300,
    "pitch": 0,
    "yaw": 4.712389,
    "roll": 0
  },
  {
    "name": "lbg_2i",
    "x": -975,
    "y": 1700,
    "z": -3300,
    "pitch": 0,
    "yaw": 0,
    "roll": 0
  },
  {
    "name": "LBG_1G",
    "x": -975,
    "y": 1700,
    "z": -3285,
    "pitch": 0,
    "yaw": 0,
    "roll": 0
  },
  {
    "name": "lbg_2b",
    "x": -900,
    "y": 1700,
    "z": -3285,
    "pitch": 0,
    "yaw": 0,
    "roll": 0
  },
  {
    "name": "lbg_3e",
    "x": -900,
    "y": 1700,
    "z": -3270,
    "pitch": 0,
    "yaw": 0,
    "roll": 0
  },
  {
    "name": "lbg_2g",
    "x": -915,
    "y": 1700,
    "z": -3270,
    "pitch": 0,
    "yaw": 0,
    "roll": 0
  },
  {
    "name": "lbg_2h",
    "x": -885,
    "y": 1700,
    "z": -3270,
    "pitch": 0,
    "yaw": 1.5707964,
    "roll": 0
  },
  {
    "name": "lbg_2e",
    "x": -885,
    "y": 1700,
    "z": -3255,
    "pitch": 0,
    "yaw": 0,
    "roll": 0
  },
  {
    "name": "lbg_2j",
    "x": -885,
    "y": 1700,
    "z": -3240,
    "pitch": 0,
    "yaw": 4.712389,
    "roll": 0
  },
  {
    "name": "lbg_2f",
    "x": -915,
    "y": 1700,
    "z": -3255,
    "pitch": 0,
    "yaw": 0,
    "roll": 0
  },
  {
    "name": "lbg_2i",
    "x": -915,
    "y": 1700,
    "z": -3240,
    "pitch": 0,
    "yaw": 4.712389,
    "roll": 0
  },
  {
    "name": "lbg_4b",
    "x": -900,
    "y": 1700,
    "z": -3240,
    "pitch": 0,
    "yaw": 4.712389,
    "roll": 0
  },
  {
    "name": "lbg_1h",
    "x": -900,
    "y": 1700,
    "z": -3255,
    "pitch": 0,
    "yaw": 1.5707964,
    "roll": 0
  },
  {
    "name": "LBG_1G",
    "x": -900,
    "y": 1700,
    "z": -3225,
    "pitch": 0,
    "yaw": 0,
    "roll": 0
  },
  {
    "name": "LBG_1G",
    "x": -700,
    "y": 1700,
    "z": -3300,
    "pitch": 0,
    "yaw": 0,
    "roll": 0
  },
  {
    "name": "lbg_2h",
    "x": -700,
    "y": 1700,
    "z": -3315,
    "pitch": 0,
    "yaw": 1.5707964,
    "roll": 0
  },
  {
    "name": "lbg_2g",
    "x": -715,
    "y": 1700,
    "z": -3315,
    "pitch": 0,
    "yaw": 0,
    "roll": 0
  },
  {
    "name": "lbg_2f",
    "x": -715,
    "y": 1700,
    "z": -3300,
    "pitch": 0,
    "yaw": 0,
    "roll": 0
  },
  {
    "name": "lbg_2i",
    "x": -715,
    "y": 1700,
    "z": -3285,
    "pitch": 0,
    "yaw": 4.712389,
    "roll": 0
  },
  {
    "name": "lbg_2e",
    "x": -700,
    "y": 1700,
    "z": -3285,
    "pitch": 0,
    "yaw": 4.712389,
    "roll": 0
  },
  {
    "name": "lbg_2k",
    "x": -685,
    "y": 1700,
    "z": -3285,
    "pitch": 0,
    "yaw": 4.712389,
    "roll": 0
  },
  {
    "name": "lbg_2a",
    "x": -685,
    "y": 1700,
    "z": -3300,
    "pitch": 0,
    "yaw": 0,
    "roll": 0
  },
  {
    "name": "lbg_2d",
    "x": -685,
    "y": 1700,
    "z": -3315,
    "pitch": 0,
    "yaw": 0,
    "roll": 0
  },
  {
    "name": "lbg_2j",
    "x": -685,
    "y": 1700,
    "z": -3330,
    "pitch": 0,
    "yaw": 3.1415927,
    "roll": 0
  },
  {
    "name": "lbg_3e",
    "x": -700,
    "y": 1700,
    "z": -3330,
    "pitch": 0,
    "yaw": 0,
    "roll": 0
  },
  {
    "name": "lbg_1f",
    "x": -700,
    "y": 1700,
    "z": -3345,
    "pitch": 0,
    "yaw": 3.1415927,
    "roll": 0
  },
  {
    "name": "lbg_2e",
    "x": -715,
    "y": 1700,
    "z": -3330,
    "pitch": 0,
    "yaw": 1.5707964,
    "roll": 0
  },
  {
    "name": "lbg_2i",
    "x": -730,
    "y": 1700,
    "z": -3330,
    "pitch": 0,
    "yaw": 0,
    "roll": 0
  },
  {
    "name": "lbg_2c",
    "x": -730,
    "y": 1700,
    "z": -3315,
    "pitch": 0,
    "yaw": 0,
    "roll": 0
  },
  {
    "name": "lbg_2d",
    "x": -730,
    "y": 1700,
    "z": -3300,
    "pitch": 0,
    "yaw": 3.1415927,
    "roll": 0
  },
  {
    "name": "lbg_2b",
    "x": -730,
    "y": 1700,
    "z": -3285,
    "pitch": 0,
    "yaw": 3.1415927,
    "roll": 0
  },
  {
    "name": "lbg_2l",
    "x": -730,
    "y": 1700,
    "z": -3270,
    "pitch": 0,
    "yaw": 4.712389,
    "roll": 0
  },
  {
    "name": "lbg_2l2l",
    "x": -715,
    "y": 1700,
    "z": -3270,
    "pitch": 0,
    "yaw": 4.712389,
    "roll": 0
  },
  {
    "name": "lbg_2l2l",
    "x": -685,
    "y": 1700,
    "z": -3270,
    "pitch": 0,
    "yaw": 1.5707964,
    "roll": 0
  },
  {
    "name": "lbg_2l",
    "x": -670,
    "y": 1700,
    "z": -3270,
    "pitch": 0,
    "yaw": 3.1415927,
    "roll": 0
  },
  {
    "name": "lbg_2g",
    "x": -670,
    "y": 1700,
    "z": -3285,
    "pitch": 0,
    "yaw": 0,
    "roll": 0
  },
  {
    "name": "lbg_2j",
    "x": -655,
    "y": 1700,
    "z": -3285,
    "pitch": 0,
    "yaw": 4.712389,
    "roll": 0
  },
  {
    "name": "lbg_2h",
    "x": -655,
    "y": 1700,
    "z": -3300,
    "pitch": 0,
    "yaw": 1.5707964,
    "roll": 0
  },
  {
    "name": "lbg_2h",
    "x": -670,
    "y": 1700,
    "z": -3300,
    "pitch": 0,
    "yaw": 4.712389,
    "roll": 0
  },
  {
    "name": "lbg_2e",
    "x": -670,
    "y": 1700,
    "z": -3315,
    "pitch": 0,
    "yaw": 0,
    "roll": 0
  },
  {
    "name": "lbg_2a",
    "x": -670,
    "y": 1700,
    "z": -3330,
    "pitch": 0,
    "yaw": 3.1415927,
    "roll": 0
  },
  {
    "name": "lbg_2f",
    "x": -670,
    "y": 1700,
    "z": -3345,
    "pitch": 0,
    "yaw": 3.1415927,
    "roll": 0
  },
  {
    "name": "lbg_2k",
    "x": -670,
    "y": 1700,
    "z": -3360,
    "pitch": 0,
    "yaw": 3.1415927,
    "roll": 0
  },
  {
    "name": "lbg_3e",
    "x": -685,
    "y": 1700,
    "z": -3360,
    "pitch": 0,
    "yaw": 3.1415927,
    "roll": 0
  },
  {
    "name": "lbg_1b",
    "x": -685,
    "y": 1700,
    "z": -3345,
    "pitch": 0,
    "yaw": 4.712389,
    "roll": 0
  },
  {
    "name": "lbg_2f",
    "x": -700,
    "y": 1700,
    "z": -3360,
    "pitch": 0,
    "yaw": 4.712389,
    "roll": 0
  },
  {
    "name": "lbg_2f",
    "x": -715,
    "y": 1700,
    "z": -3360,
    "pitch": 0,
    "yaw": 4.712389,
    "roll": 0
  },
  {
    "name": "lbg_3c",
    "x": -730,
    "y": 1700,
    "z": -3360,
    "pitch": 0,
    "yaw": 3.1415927,
    "roll": 0
  },
  {
    "name": "lbg_3b",
    "x": -730,
    "y": 1700,
    "z": -3345,
    "pitch": 0,
    "yaw": 0,
    "roll": 0
  },
  {
    "name": "lbg_1h",
    "x": -715,
    "y": 1700,
    "z": -3345,
    "pitch": 0,
    "yaw": 3.1415927,
    "roll": 0
  },
  {
    "name": "lbg_2i",
    "x": -745,
    "y": 1700,
    "z": -3360,
    "pitch": 0,
    "yaw": 0,
    "roll": 0
  },
  {
    "name": "lbg_4a",
    "x": -745,
    "y": 1700,
    "z": -3345,
    "pitch": 0,
    "yaw": 0,
    "roll": 0
  },
  {
    "name": "lbg_1c",
    "x": -760,
    "y": 1700,
    "z": -3345,
    "pitch": 0,
    "yaw": 1.5707964,
    "roll": 0
  },
  {
    "name": "lbg_2e",
    "x": -745,
    "y": 1700,
    "z": -3330,
    "pitch": 0,
    "yaw": 3.1415927,
    "roll": 0
  },
  {
    "name": "lbg_2d",
    "x": -745,
    "y": 1700,
    "z": -3315,
    "pitch": 0,
    "yaw": 3.1415927,
    "roll": 0
  },
  {
    "name": "lbg_2e",
    "x": -745,
    "y": 1700,
    "z": -3300,
    "pitch": 0,
    "yaw": 0,
    "roll": 0
  },
  {
    "name": "lbg_2f",
    "x": -745,
    "y": 1700,
    "z": -3285,
    "pitch": 0,
    "yaw": 0,
    "roll": 0
  },
  {
    "name": "lbg_2c",
    "x": -745,
    "y": 1700,
    "z": -3270,
    "pitch": 0,
    "yaw": 0,
    "roll": 0
  },
  {
    "name": "lbg_2j",
    "x": -745,
    "y": 1700,
    "z": -3255,
    "pitch": 0,
    "yaw": 0,
    "roll": 0
  },
  {
    "name": "lbg_2c",
    "x": -730,
    "y": 1700,
    "z": -3255,
    "pitch": 0,
    "yaw": 1.5707964,
    "roll": 0
  },
  {
    "name": "lbg_2b",
    "x": -715,
    "y": 1700,
    "z": -3255,
    "pitch": 0,
    "yaw": 1.5707964,
    "roll": 0
  },
  {
    "name": "lbg_2a",
    "x": -700,
    "y": 1700,
    "z": -3255,
    "pitch": 0,
    "yaw": 4.712389,
    "roll": 0
  },
  {
    "name": "LBG_1G",
    "x": -685,
    "y": 1700,
    "z": -3255,
    "pitch": 0,
    "yaw": 4.712389,
    "roll": 0
  },
  {
    "name": "lbg_2d",
    "x": -700,
    "y": 1710,
    "z": -3270,
    "pitch": 0,
    "yaw": 1.5707964,
    "roll": 0
  }
]